[
  {
    "CellType": "Live",
    "Cells": [
      {
        "PosX": 1501.2692307692307,
        "PosY": 21.73076923076923,
        "RadiusMajor": 4.318667337691257,
        "RadiusMinor": 3.679464843989783,
        "OrientationDegrees": -45.00000000352163,
        "Size": 5.045027830476039,
        "Circularity": 73.18068343242699,
        "Brightness": 85.53846153846153,
        "IsFluorescent": null,
        "FluorescentBrightness": null,
        "IsValid": true
      },
      {
        "PosX": 2368.0652173913045,
        "PosY": 411.54347826086956,
        "RadiusMajor": 6.513969010878364,
        "RadiusMinor": 4.618034403299005,
        "OrientationDegrees": 37.18520220727638,
        "Size": 7.8720975970545695,
        "Circularity": 77.73778073952836,
        "Brightness": 77.17391304347827,
        "IsFluorescent": null,
        "FluorescentBrightness": null,
        "IsValid": true
      },
      {
        "PosX": 1421.7727272727273,
        "PosY": 497.77272727272725,
        "RadiusMajor": 4.610834905652909,
        "RadiusMinor": 3.0688576741454034,
        "OrientationDegrees": 30.28627179802775,
        "Size": 5.421275937170197,
        "Circularity": 66.04611745029894,
        "Brightness": 86.0909090909091,
        "IsFluorescent": null,
        "FluorescentBrightness": null,
        "IsValid": true
      },
      {
        "PosX": 1081.3,
        "PosY": 501.46,
        "RadiusMajor": 6.321500917341829,
        "RadiusMinor": 5.047001699253592,
        "OrientationDegrees": -64.48800345934448,
        "Size": 7.624240669273796,
        "Circularity": 81.36323689712341,
        "Brightness": 93.84,
        "IsFluorescent": null,
        "FluorescentBrightness": null,
        "IsValid": true
      },
      {
        "PosX": 1325.5,
        "PosY": 616.0555555555555,
        "RadiusMajor": 5.25873758497607,
        "RadiusMinor": 4.268749491597657,
        "OrientationDegrees": -90.0,
        "Size": 6.255633282573458,
        "Circularity": 59.357073584287534,
        "Brightness": 86.44444444444444,
        "IsFluorescent": null,
        "FluorescentBrightness": null,
        "IsValid": true
      },
      {
        "PosX": 368.08490566037733,
        "PosY": 874.688679245283,
        "RadiusMajor": 10.268544097966734,
        "RadiusMinor": 8.546703700944889,
        "OrientationDegrees": -80.78571116543442,
        "Size": 12.707171448042246,
        "Circularity": 79.3720246091969,
        "Brightness": 87.62264150943396,
        "IsFluorescent": null,
        "FluorescentBrightness": null,
        "IsValid": true
      },
      {
        "PosX": 1723.7380952380952,
        "PosY": 1492.0238095238096,
        "RadiusMajor": 5.4809503124710135,
        "RadiusMinor": 4.8860020336585,
        "OrientationDegrees": -14.036243458766046,
        "Size": 6.541794811680244,
        "Circularity": 76.82574741753156,
        "Brightness": 116.28571428571429,
        "IsFluorescent": null,
        "FluorescentBrightness": null,
        "IsValid": true
      },
      {
        "PosX": 1417.5,
        "PosY": 1622.8333333333333,
        "RadiusMajor": 6.0057290970652035,
        "RadiusMinor": 3.1864463335418467,
        "OrientationDegrees": -33.91682708910002,
        "Size": 7.217595433612177,
        "Circularity": 58.80116163637354,
        "Brightness": 103.0,
        "IsFluorescent": null,
        "FluorescentBrightness": null,
        "IsValid": true
      },
      {
        "PosX": 2504.233333333333,
        "PosY": 1685.4333333333334,
        "RadiusMajor": 4.61880215370283,
        "RadiusMinor": 4.061745656433896,
        "OrientationDegrees": -14.036243431575553,
        "Size": 5.4315360150264045,
        "Circularity": 81.34306290267284,
        "Brightness": 97.26666666666667,
        "IsFluorescent": null,
        "FluorescentBrightness": null,
        "IsValid": true
      },
      {
        "PosX": 875.5769230769231,
        "PosY": 1688.8076923076924,
        "RadiusMajor": 4.361664559688937,
        "RadiusMinor": 3.756591133295703,
        "OrientationDegrees": 13.776405776634181,
        "Size": 5.100398874848285,
        "Circularity": 52.090612213798536,
        "Brightness": 106.84615384615384,
        "IsFluorescent": null,
        "FluorescentBrightness": null,
        "IsValid": true
      },
      {
        "PosX": 1462.735294117647,
        "PosY": 1792.3823529411766,
        "RadiusMajor": 4.998895841318765,
        "RadiusMinor": 4.566384873908556,
        "OrientationDegrees": -127.23794451543135,
        "Size": 5.921013787421274,
        "Circularity": 71.65317044117411,
        "Brightness": 79.76470588235294,
        "IsFluorescent": null,
        "FluorescentBrightness": null,
        "IsValid": true
      }
    ],
    "Cube": null,
    "UIColor": "#ff51cc5b",
    "FluorescentIndex": null,
    "GatingParameters": {
      "MinSize": 0.0,
      "MaxSize": 70.0,
      "MinBrightness": 0.0,
      "MaxBrightness": 255.0,
      "MinCircularity": 0.0,
      "MaxCircularity": 100.0,
      "ParameterChanged": {
        "HasObservers": true,
        "IsDisposed": false,
        "Value": {}
      }
    },
    "PendingGatingParameters": {
      "MinSize": 0.0,
      "MaxSize": 70.0,
      "MinBrightness": 0.0,
      "MaxBrightness": 255.0,
      "MinCircularity": 0.0,
      "MaxCircularity": 100.0,
      "ParameterChanged": {
        "HasObservers": false,
        "IsDisposed": false,
        "Value": {}
      }
    },
    "Concentration": 57549.530522,
    "GatedCount": 11,
    "LightIntensity": 89.0,
    "NormalizedLightIntensity": 35.0,
    "CameraBinning": 1
  },
  {
    "CellType": "Dead",
    "Cells": [
      {
        "PosX": 1876.9285714285713,
        "PosY": 7.785714285714286,
        "RadiusMajor": 4.93871596743298,
        "RadiusMinor": 3.7385065912760522,
        "OrientationDegrees": -96.80027125910985,
        "Size": 5.843515234900237,
        "Circularity": 65.47394645941279,
        "Brightness": 76.28571428571429,
        "IsFluorescent": null,
        "FluorescentBrightness": null,
        "IsValid": true
      },
      {
        "PosX": 686.7962962962963,
        "PosY": 53.092592592592595,
        "RadiusMajor": 6.314006402372111,
        "RadiusMinor": 5.430341090384291,
        "OrientationDegrees": -55.405660878034055,
        "Size": 7.614589368523271,
        "Circularity": 79.90643762497224,
        "Brightness": 79.62962962962963,
        "IsFluorescent": null,
        "FluorescentBrightness": null,
        "IsValid": true
      },
      {
        "PosX": 1953.625,
        "PosY": 189.75,
        "RadiusMajor": 7.689570333763241,
        "RadiusMinor": 5.436727699830873,
        "OrientationDegrees": 4.6216665755791775,
        "Size": 9.386015705927752,
        "Circularity": 80.38075448555892,
        "Brightness": 75.5625,
        "IsFluorescent": null,
        "FluorescentBrightness": null,
        "IsValid": true
      },
      {
        "PosX": 110.5,
        "PosY": 328.5,
        "RadiusMajor": 5.327693424802254,
        "RadiusMinor": 2.9221156196173053,
        "OrientationDegrees": -104.87244064842943,
        "Size": 6.344433365214775,
        "Circularity": 78.2986331326774,
        "Brightness": 102.46153846153847,
        "IsFluorescent": null,
        "FluorescentBrightness": null,
        "IsValid": true
      },
      {
        "PosX": 121.58333333333333,
        "PosY": 340.6666666666667,
        "RadiusMajor": 7.4942924336287025,
        "RadiusMinor": 4.1267451294764,
        "OrientationDegrees": 36.00758855440452,
        "Size": 9.134540360058855,
        "Circularity": 70.36761132931123,
        "Brightness": 105.41666666666667,
        "IsFluorescent": null,
        "FluorescentBrightness": null,
        "IsValid": true
      },
      {
        "PosX": 134.6290322580645,
        "PosY": 349.7258064516129,
        "RadiusMajor": 6.986997621615003,
        "RadiusMinor": 5.952095577095987,
        "OrientationDegrees": 39.98775660184461,
        "Size": 8.481255281610398,
        "Circularity": 81.32255566194493,
        "Brightness": 97.90322580645162,
        "IsFluorescent": null,
        "FluorescentBrightness": null,
        "IsValid": true
      },
      {
        "PosX": 139.47435897435898,
        "PosY": 360.3974358974359,
        "RadiusMajor": 7.6179009259550075,
        "RadiusMinor": 6.662163050732607,
        "OrientationDegrees": -77.50756064785753,
        "Size": 9.293721139546316,
        "Circularity": 76.62397182759972,
        "Brightness": 97.94871794871794,
        "IsFluorescent": null,
        "FluorescentBrightness": null,
        "IsValid": true
      },
      {
        "PosX": 367.77272727272725,
        "PosY": 871.9545454545455,
        "RadiusMajor": 4.348458452010604,
        "RadiusMinor": 3.3525616208408726,
        "OrientationDegrees": -113.19859051514769,
        "Size": 5.083392288369719,
        "Circularity": 67.35911106686225,
        "Brightness": 61.36363636363637,
        "IsFluorescent": null,
        "FluorescentBrightness": null,
        "IsValid": true
      },
      {
        "PosX": 960.0,
        "PosY": 1293.6666666666667,
        "RadiusMajor": 4.418071998168503,
        "RadiusMinor": 3.371873174749424,
        "OrientationDegrees": -122.06682160415782,
        "Size": 5.173039353322574,
        "Circularity": 64.2404199652016,
        "Brightness": 82.0,
        "IsFluorescent": null,
        "FluorescentBrightness": null,
        "IsValid": true
      },
      {
        "PosX": 1414.5,
        "PosY": 1619.590909090909,
        "RadiusMajor": 4.077022084914039,
        "RadiusMinor": 3.677859601976282,
        "OrientationDegrees": -54.99155326905027,
        "Size": 4.73384144697918,
        "Circularity": 59.070482214064235,
        "Brightness": 94.27272727272727,
        "IsFluorescent": null,
        "FluorescentBrightness": null,
        "IsValid": true
      },
      {
        "PosX": 561.6612903225806,
        "PosY": 1713.4032258064517,
        "RadiusMajor": 6.425754631155791,
        "RadiusMinor": 6.063143290042225,
        "OrientationDegrees": -120.96375653805168,
        "Size": 7.758496715254527,
        "Circularity": 86.06025820758434,
        "Brightness": 120.61290322580645,
        "IsFluorescent": null,
        "FluorescentBrightness": null,
        "IsValid": true
      },
      {
        "PosX": 2522.7926829268295,
        "PosY": 1908.5,
        "RadiusMajor": 7.537069466277072,
        "RadiusMinor": 6.887328693302535,
        "OrientationDegrees": -46.04762628980576,
        "Size": 9.189627848571801,
        "Circularity": 79.63398383095816,
        "Brightness": 102.97560975609755,
        "IsFluorescent": null,
        "FluorescentBrightness": null,
        "IsValid": true
      }
    ],
    "Cube": null,
    "UIColor": "#ffc83c3c",
    "FluorescentIndex": null,
    "GatingParameters": {
      "MinSize": 0.0,
      "MaxSize": 70.0,
      "MinBrightness": 0.0,
      "MaxBrightness": 255.0,
      "MinCircularity": 0.0,
      "MaxCircularity": 100.0,
      "ParameterChanged": {
        "HasObservers": true,
        "IsDisposed": false,
        "Value": {}
      }
    },
    "PendingGatingParameters": {
      "MinSize": 0.0,
      "MaxSize": 70.0,
      "MinBrightness": 0.0,
      "MaxBrightness": 255.0,
      "MinCircularity": 0.0,
      "MaxCircularity": 100.0,
      "ParameterChanged": {
        "HasObservers": false,
        "IsDisposed": false,
        "Value": {}
      }
    },
    "Concentration": 62781.306024000005,
    "GatedCount": 12,
    "LightIntensity": 89.0,
    "NormalizedLightIntensity": 35.0,
    "CameraBinning": 1
  }
]